<?xml version="1.0" encoding="utf-8" ?>
<dwsync>
<file name="bootstrap-theme.css" server="ftp.beatblab.com/mrchalkies/installify/" local="130928564600000000" remote="130953048600000000" Dst="0" />
<file name="bootstrap-theme.min.css" server="ftp.beatblab.com/mrchalkies/installify/" local="130928564600000000" remote="130953048600000000" Dst="0" />
<file name="bootstrap-theme.css.map" server="ftp.beatblab.com/mrchalkies/installify/" local="130928564600000000" remote="130953048600000000" Dst="0" />
<file name="bootstrap-theme.min.css.map" server="ftp.beatblab.com/mrchalkies/installify/" local="130928564600000000" remote="130953048600000000" Dst="0" />
<file name="bootstrap.css" server="ftp.beatblab.com/mrchalkies/installify/" local="130928564600000000" remote="130953048600000000" Dst="0" />
<file name="bootstrap.min.css" server="ftp.beatblab.com/mrchalkies/installify/" local="130928564600000000" remote="130953048600000000" Dst="0" />
<file name="bootstrap.min.css.map" server="ftp.beatblab.com/mrchalkies/installify/" local="130928564600000000" remote="130953048600000000" Dst="0" />
<file name="bootstrap.css.map" server="ftp.beatblab.com/mrchalkies/installify/" local="130928564600000000" remote="130953049200000000" Dst="0" />
</dwsync>